{
  "hash": "6b7c5d36",
  "browserHash": "61380f0b",
  "optimized": {
    "vue": {
      "src": "../../node_modules/vue/dist/vue.runtime.esm-bundler.js",
      "file": "vue.js",
      "fileHash": "6b6bbc55",
      "needsInterop": false
    },
    "pinia": {
      "src": "../../node_modules/pinia/dist/pinia.mjs",
      "file": "pinia.js",
      "fileHash": "391fab15",
      "needsInterop": false
    },
    "vue-router": {
      "src": "../../node_modules/vue-router/dist/vue-router.mjs",
      "file": "vue-router.js",
      "fileHash": "e5720f5c",
      "needsInterop": false
    }
  },
  "chunks": {
    "chunk-3GOOGFKQ": {
      "file": "chunk-3GOOGFKQ.js"
    },
    "chunk-RY4PZZFY": {
      "file": "chunk-RY4PZZFY.js"
    }
  }
}